4-bit-ALU/rtl/alu.v
module alu (
    input  [3:0] A,
    input  [3:0] B,
    input  [2:0] sel,
    output reg [3:0] result
);

always @(*) begin
    case (sel)
        3'b000: result = A + B;      // Addition
        3'b001: result = A - B;      // Subtraction
        3'b010: result = A & B;      // AND
        3'b011: result = A | B;      // OR
        3'b100: result = A ^ B;      // XOR
        3'b101: result = ~A;         // NOT A
        3'b110: result = A << 1;     // Left Shift
        3'b111: result = A >> 1;     // Right Shift
        default: result = 4'b0000;
    endcase
end

endmodule

4-bit-ALU/tb/alu_tb.v
`timescale 1ns/1ps

module alu_tb;

    // Inputs
    reg [3:0] A;
    reg [3:0] B;
    reg [2:0] sel;

    // Output
    wire [3:0] result;

    // Instantiate the ALU
    alu uut (
        .A(A),
        .B(B),
        .sel(sel),
        .result(result)
    );

    // Generate VCD file for GTKWave
    initial begin
        $dumpfile("alu.vcd");
        $dumpvars(0, alu_tb);
    end

    // Apply test cases
    initial begin

        $display("Time\tA\tB\tsel\tResult");
        $monitor("%0t\t%b\t%b\t%b\t%b",
                 $time, A, B, sel, result);

        // Test values
        A = 4'b0101;   // 5
        B = 4'b0011;   // 3

        sel = 3'b000; #10;   // Add
        sel = 3'b001; #10;   // Subtract
        sel = 3'b010; #10;   // AND
        sel = 3'b011; #10;   // OR
        sel = 3'b100; #10;   // XOR
        sel = 3'b101; #10;   // NOT A
        sel = 3'b110; #10;   // Left Shift
        sel = 3'b111; #10;   // Right Shift

        $finish;

    end

endmodule

4-bit-ALU/alu.vcd
$date
	Tue Jul 28 12:30:23 2026
$end
$version
	Icarus Verilog
$end
$timescale
	1ps
$end
$scope module alu_tb $end
$var wire 4 ! result [3:0] $end
$var reg 4 " A [3:0] $end
$var reg 4 # B [3:0] $end
$var reg 3 $ sel [2:0] $end
$scope module uut $end
$var wire 4 % A [3:0] $end
$var wire 4 & B [3:0] $end
$var wire 3 ' sel [2:0] $end
$var reg 4 ( result [3:0] $end
$upscope $end
$upscope $end
$enddefinitions $end
$comment Show the parameter values. $end
$dumpall
$end
#0
$dumpvars
b1000 (
b0 '
b11 &
b101 %
b0 $
b11 #
b101 "
b1000 !
$end
#10000
b10 !
b10 (
b1 $
b1 '
#20000
b1 !
b1 (
b10 $
b10 '
#30000
b111 !
b111 (
b11 $
b11 '
#40000
b110 !
b110 (
b100 $
b100 '
#50000
b1010 !
b1010 (
b101 $
b101 '
#60000
b110 $
b110 '
#70000
b10 !
b10 (
b111 $
b111 '
